direct_data_driven_mpc/__init__.py
direct_data_driven_mpc/lti_data_driven_mpc_controller.py
direct_data_driven_mpc/nonlinear_data_driven_mpc_controller.py
direct_data_driven_mpc/utilities/__init__.py
direct_data_driven_mpc/utilities/hankel_matrix_utils.py
direct_data_driven_mpc/utilities/initial_state_estimation.py
direct_data_driven_mpc/utilities/yaml_config_loading.py
direct_data_driven_mpc/utilities/controller/__init__.py
direct_data_driven_mpc/utilities/controller/controller_creation.py
direct_data_driven_mpc/utilities/controller/controller_params.py
direct_data_driven_mpc/utilities/controller/data_driven_mpc_sim.py
direct_data_driven_mpc/utilities/controller/initial_data_generation.py
direct_data_driven_mpc/utilities/models/__init__.py
direct_data_driven_mpc/utilities/models/lti_model.py
direct_data_driven_mpc/utilities/models/nonlinear_model.py
direct_data_driven_mpc/utilities/visualization/__init__.py
direct_data_driven_mpc/utilities/visualization/comparison_plot.py
direct_data_driven_mpc/utilities/visualization/control_plot.py
direct_data_driven_mpc/utilities/visualization/control_plot_anim.py
direct_data_driven_mpc/utilities/visualization/plot_utilities.py
direct_data_driven_mpc-1.3.0.dist-info/licenses/LICENSE
direct_data_driven_mpc-1.3.0.dist-info/METADATA
direct_data_driven_mpc-1.3.0.dist-info/WHEEL
direct_data_driven_mpc-1.3.0.dist-info/top_level.txt
direct_data_driven_mpc-1.3.0.dist-info/RECORD
