Metadata-Version: 2.4
Name: direct-data-driven-mpc
Version: 1.3.0
Summary: Robust and nonlinear Direct Data-Driven MPC controllers for LTI and nonlinear systems in Python
Author-email: "Pável A. Campos-Peña" <pcamposp@uni.pe>
License-Expression: MIT
Project-URL: Homepage, https://github.com/pavelacamposp/direct-data-driven-mpc
Keywords: data-driven,mpc,model-predictive-control,robust-control,nonlinear-control,data-driven-control
Classifier: Programming Language :: Python :: 3
Classifier: Programming Language :: Python :: 3.10
Classifier: Programming Language :: Python :: 3.11
Classifier: Programming Language :: Python :: 3.12
Classifier: Operating System :: OS Independent
Requires-Python: >=3.10.0
License-File: LICENSE
Requires-Dist: numpy
Requires-Dist: matplotlib>=3.9.0
Requires-Dist: clarabel==0.10.0
Requires-Dist: cvxpy
Requires-Dist: tqdm
Requires-Dist: PyYAML
Requires-Dist: PyQt6
Provides-Extra: dev
Requires-Dist: pre-commit; extra == "dev"
Requires-Dist: mypy==1.16.1; extra == "dev"
Dynamic: license-file
